[
  {
    "line": 1,
    "elements": [
      {
        "before": [
          {
            "result": {
              "duration": 9163098200,
              "status": "passed"
            },
            "match": {
              "location": "Hooks.openBrowser()"
            }
          }
        ],
        "line": 5,
        "name": "User is on a HomePage",
        "description": "",
        "id": "broadband-and-tv-packages--availability-functionality;user-is-on-a-homepage",
        "after": [
          {
            "result": {
              "duration": 1655355300,
              "status": "passed"
            },
            "match": {
              "location": "Hooks.tearDown(Scenario)"
            }
          }
        ],
        "type": "scenario",
        "keyword": "Scenario",
        "steps": [
          {
            "result": {
              "duration": 3679838000,
              "status": "passed"
            },
            "line": 6,
            "name": "User Enter PostCode \"Ha0 2hl\" on Postcode field",
            "match": {
              "arguments": [
                {
                  "val": "Ha0 2hl",
                  "offset": 21
                }
              ],
              "location": "AvailabilityStepdefs.userEnterPostCodeOnPostcodeField(String)"
            },
            "keyword": "When "
          },
          {
            "result": {
              "duration": 17659993200,
              "status": "passed"
            },
            "line": 7,
            "name": "Click on search button",
            "match": {
              "location": "AvailabilityStepdefs.clickOnSearchButton()"
            },
            "keyword": "And "
          }
        ],
        "tags": [
          {
            "line": 4,
            "name": "@Smoke"
          }
        ]
      }
    ],
    "name": "Broadband and tv Packages  Availability Functionality",
    "description": "User want to check which broadband and TV packages are available as per user postcode .",
    "id": "broadband-and-tv-packages--availability-functionality",
    "keyword": "Feature",
    "uri": "src/test/java/resources/feature_File/Availability.feature"
  }
]